bio2csv/__init__.py
bio2csv-0.0.1.dist-info/LICENSE
bio2csv-0.0.1.dist-info/METADATA
bio2csv-0.0.1.dist-info/WHEEL
bio2csv-0.0.1.dist-info/top_level.txt
bio2csv-0.0.1.dist-info/RECORD
