Metadata-Version: 2.1
Name: bio2csv
Version: 0.0.1
Summary: the easiest way to download many articles from biorxiv
Home-page: https://github.com/andrewgcodes
Author: Andrew Gao
Author-email: gaodrew@stanford.edu
Classifier: Programming Language :: Python :: 3
Classifier: License :: OSI Approved :: MIT License
Classifier: Operating System :: OS Independent
Requires-Python: >=3.6
License-File: LICENSE
